heslserv/__init__.py
heslserv/server.py
heslserv/templates/index.html
hesl_serv-1.0.dist-info/METADATA
hesl_serv-1.0.dist-info/WHEEL
hesl_serv-1.0.dist-info/entry_points.txt
hesl_serv-1.0.dist-info/top_level.txt
hesl_serv-1.0.dist-info/RECORD
